tests
thriftpl
