Metadata-Version: 1.0
Name: thriftpl
Version: 0.2.0
Summary: a thrift client pool for python
Home-page: http://git.oschina.net/hand515/python-thrift-pool
Author: tanghd
Author-email: hand515@gmail.com
License: LGPL
Platform: UNKNOWN
